snqueue/__init__.py
snqueue/settings.py
snqueue/boto3_clients/__init__.py
snqueue/boto3_clients/boto3_base_client.py
snqueue/boto3_clients/kms_client.py
snqueue/boto3_clients/s3_client.py
snqueue/boto3_clients/ses_client.py
snqueue/boto3_clients/sns_client.py
snqueue/boto3_clients/sqs_client.py
snqueue/service/__init__.py
snqueue/service/client.py
snqueue/service/helper.py
snqueue/service/server.py
snqueue/utils/email.py
snqueue-0.7.1.dist-info/METADATA
snqueue-0.7.1.dist-info/WHEEL
snqueue-0.7.1.dist-info/top_level.txt
snqueue-0.7.1.dist-info/RECORD
