Metadata-Version: 2.1
Name: snqueue
Version: 0.7.1
Summary: A message-driven req/res implementation using AWS SNS/SQS
Requires-Dist: boto3
Requires-Dist: pycryptodomex
Requires-Dist: pydantic[email]
Requires-Dist: pydantic-settings
Requires-Dist: python-dateutil
